aldryn_common/__init__.py
aldryn_common/paginator.py
aldryn_common/slugs.py
aldryn_common/timesince.py
aldryn_common/tools.py
aldryn_common/admin_fields/__init__.py
aldryn_common/admin_fields/sortedm2m.py
aldryn_common/boilerplates/bootstrap3/templates/aldryn_common/paginator.html
aldryn_common/boilerplates/legacy/templates/aldryn_common/paginator.html
aldryn_common/templates/admin/aldryn_common/widgets/sortedm2m_widget.html
aldryn_common/templatetags/__init__.py
aldryn_common/templatetags/date_range.py
aldryn_common/templatetags/html_filter_tags.py
aldryn_common/templatetags/query_string_tools.py
aldryn_common/templatetags/string_tags.py
djangocms_aldryn_common-2.0.2.dist-info/LICENSE.txt
djangocms_aldryn_common-2.0.2.dist-info/METADATA
djangocms_aldryn_common-2.0.2.dist-info/WHEEL
djangocms_aldryn_common-2.0.2.dist-info/top_level.txt
djangocms_aldryn_common-2.0.2.dist-info/RECORD
